xboxswitchbridge/__init__.py
xboxswitchbridge/bridge.py
xboxswitchbridge/cli.py
xboxswitchbridge/service.py
xbox_switch_bridge-0.4.0.dist-info/LICENSE
xbox_switch_bridge-0.4.0.dist-info/METADATA
xbox_switch_bridge-0.4.0.dist-info/WHEEL
xbox_switch_bridge-0.4.0.dist-info/entry_points.txt
xbox_switch_bridge-0.4.0.dist-info/top_level.txt
xbox_switch_bridge-0.4.0.dist-info/RECORD
