Metadata-Version: 2.2
Name: xbox-switch-bridge
Version: 0.4.0
Summary: Bridge Xbox controller inputs to Nintendo Switch
Home-page: https://github.com/l-carta/xbox-switch-bridge
Author: Leonardo Carta
Author-email: leonardo@carta.vision
Project-URL: Bug Tracker, https://github.com/l-carta/xbox-switch-bridge/issues
Classifier: Programming Language :: Python :: 3.9
Classifier: License :: OSI Approved :: MIT License
Classifier: Operating System :: POSIX :: Linux
Classifier: Topic :: Games/Entertainment
Requires-Python: >=3.9
License-File: LICENSE
Requires-Dist: evdev>=1.4.0
Requires-Dist: nxbt>=0.1.0
Requires-Dist: asyncio>=3.4.3
Requires-Dist: dbus-python>=1.2.16
Requires-Dist: pygobject>=3.40.0
Requires-Dist: systemd-python
